<?xml version="1.0"?>
<palette guid="c3c2ab44-99cc-4894-8b03-90d043a35dc6" name="Paleta de documentos"><colors><page><color cs="RGB" name="Amarelo" tints="1,1,0"/><color cs="RGB" name="R102 G50 B0" tints="0.4,0.196078,0"/><color cs="RGB" name="R207 G166 B128" tints="0.811765,0.65098,0.501961"/><color cs="RGB" name="R230 G215 B200" tints="0.901961,0.843137,0.784314"/><color cs="RGB" name="R195 G177 B155" tints="0.764706,0.694118,0.607843"/><color cs="RGB" name="R127 G101 B76" tints="0.498039,0.396078,0.298039"/><color cs="RGB" name="Preto" tints="0,0,0"/><color cs="RGB" name="Branco" tints="1,1,1"/><color cs="RGB" name="Vermelho" tints="1,0,0"/></page></colors></palette>
